make_it_sync/__init__.py
make_it_sync/func_wrapper.py
make_it_sync-2.0.0.dist-info/METADATA
make_it_sync-2.0.0.dist-info/WHEEL
make_it_sync-2.0.0.dist-info/licenses/LICENSE
make_it_sync-2.0.0.dist-info/RECORD
