Metadata-Version: 2.3
Name: make-it-sync
Version: 2.0.0
Summary: Create a sync version of an async function
Project-URL: Documentation, https://github.com/gordonwatts/make-it-sync
Project-URL: Homepage, https://github.com/gordonwatts/make-it-sync
Project-URL: Issues, https://github.com/gordonwatts/make-it-sync/issues
Project-URL: Release Notes, https://github.com/gordonwatts/make-it-sync/releases
Project-URL: Releases, https://github.com/gordonwatts/make-it-sync/releases
Project-URL: Source Code, https://github.com/gordonwatts/make-it-sync
Author-email: Gordon Watts <gwatts@uw.edu>
License-Expression: MIT
License-File: LICENSE
Classifier: Development Status :: 3 - Alpha
Classifier: Intended Audience :: Developers
Classifier: Intended Audience :: Information Technology
Classifier: Programming Language :: Python
Classifier: Programming Language :: Python :: 3.7
Classifier: Programming Language :: Python :: 3.8
Classifier: Programming Language :: Python :: 3.9
Classifier: Programming Language :: Python :: 3.10
Classifier: Programming Language :: Python :: 3.11
Classifier: Programming Language :: Python :: 3.12
Classifier: Programming Language :: Python :: Implementation :: CPython
Classifier: Topic :: Software Development
Classifier: Topic :: Utilities
Requires-Python: >=3.7
Provides-Extra: test
Requires-Dist: autopep8; extra == 'test'
Requires-Dist: build; extra == 'test'
Requires-Dist: codecov; extra == 'test'
Requires-Dist: coverage; extra == 'test'
Requires-Dist: flake8; extra == 'test'
Requires-Dist: pytest-asyncio; extra == 'test'
Requires-Dist: pytest-cov; extra == 'test'
Requires-Dist: pytest-mock; extra == 'test'
Requires-Dist: pytest>=3.9; extra == 'test'
Requires-Dist: twine; extra == 'test'
Requires-Dist: wheel; extra == 'test'
